[
  {
    "full_name": "cardano-foundation/developer-portal",
    "stargazers_count": 261,
    "open_issues_count": 35,
    "forks_count": 654
  },
  {
    "full_name": "hashicorp/terraform",
    "stargazers_count": 35010,
    "open_issues_count": 1688,
    "forks_count": 8092
  },
  {
    "full_name": "forem/forem",
    "stargazers_count": 19884,
    "open_issues_count": 515,
    "forks_count": 3539
  },
  {
    "full_name": "open-sauced/open-sauced",
    "stargazers_count": 805,
    "open_issues_count": 9,
    "forks_count": 431
  }
]