[
  {
    "full_name": "cardano-foundation/developer-portal",
    "stargazers_count": 296,
    "open_issues_count": 31,
    "forks_count": 725
  },
  {
    "full_name": "hashicorp/terraform",
    "stargazers_count": 36261,
    "open_issues_count": 1751,
    "forks_count": 8389
  },
  {
    "full_name": "forem/forem",
    "stargazers_count": 20250,
    "open_issues_count": 552,
    "forks_count": 3610
  },
  {
    "full_name": "open-sauced/open-sauced",
    "stargazers_count": 842,
    "open_issues_count": 9,
    "forks_count": 537
  }
]