[
  {
    "full_name": "cardano-foundation/developer-portal",
    "stargazers_count": 423,
    "open_issues_count": 31,
    "forks_count": 1060
  },
  {
    "full_name": "hashicorp/terraform",
    "stargazers_count": 47105,
    "open_issues_count": 1910,
    "forks_count": 10115
  },
  {
    "full_name": "forem/forem",
    "stargazers_count": 22514,
    "open_issues_count": 593,
    "forks_count": 4152
  },
  {
    "full_name": "open-sauced/open-sauced",
    "stargazers_count": 954,
    "open_issues_count": 0,
    "forks_count": 1161
  }
]