[
  {
    "full_name": "cardano-foundation/developer-portal",
    "stargazers_count": 236,
    "open_issues_count": 28,
    "forks_count": 593
  },
  {
    "full_name": "hashicorp/terraform",
    "stargazers_count": 33513,
    "open_issues_count": 1650,
    "forks_count": 7772
  },
  {
    "full_name": "forem/forem",
    "stargazers_count": 19383,
    "open_issues_count": 500,
    "forks_count": 3439
  },
  {
    "full_name": "open-sauced/open-sauced",
    "stargazers_count": 726,
    "open_issues_count": 16,
    "forks_count": 320
  }
]