[
  {
    "full_name": "cardano-foundation/developer-portal",
    "stargazers_count": 363,
    "open_issues_count": 25,
    "forks_count": 860
  },
  {
    "full_name": "hashicorp/terraform",
    "stargazers_count": 41006,
    "open_issues_count": 1960,
    "forks_count": 9269
  },
  {
    "full_name": "forem/forem",
    "stargazers_count": 21520,
    "open_issues_count": 617,
    "forks_count": 3910
  },
  {
    "full_name": "open-sauced/open-sauced",
    "stargazers_count": 917,
    "open_issues_count": 0,
    "forks_count": 862
  }
]